{
    "Card1":{
        "Img": "https://github.com/Apexofacircle/GitShopProduct1/raw/main/IMG_0242.jpg",
        "Name" : "bat",
        "Description" : "Placeholder Lorem Blablabla",
        "Detailed_Description" : "Detailed_Description",
        "Download" : "link to download"
    },

    "Card2":{
        "Img": "https://github.com/Apexofacircle/GitShopProduct1/raw/main/IMG_0242.jpg",
        "Name" : "Card2",
        "Description" : "Placeholder Lorem",
        "Download" : "link to download"
    },

    "Card3":{
        "Img": "https://github.com/Apexofacircle/GitShopProduct1/raw/main/IMG_0242.jpg",
        "Name" : "Card2",
        "Description" : "Placeholder Lorem",
        "Download" : "link to download"
    }
}